drive_files_gen.py
drive_files_gen-0.0.4.dist-info/LICENSE
drive_files_gen-0.0.4.dist-info/METADATA
drive_files_gen-0.0.4.dist-info/WHEEL
drive_files_gen-0.0.4.dist-info/top_level.txt
drive_files_gen-0.0.4.dist-info/RECORD
