Metadata-Version: 2.1
Name: drive-files-gen
Version: 0.0.4
Summary: Tool to generate files on Google Drive from a JSON file
Home-page: https://github.com/Vallenain/Drive-files-generator
Author: Val Le Nain
Author-email: vallenain@gmail.com
License: UNKNOWN
Keywords: google-drive JSON automation
Platform: UNKNOWN
Classifier: Programming Language :: Python :: 3
Classifier: License :: OSI Approved :: MIT License
Classifier: Operating System :: OS Independent
Classifier: Topic :: Utilities
Requires-Python: >=3.6
Requires-Dist: google-auth
Requires-Dist: google-auth-oauthlib
Requires-Dist: google-api-python-client
